defectdojo_utils/__init__.py
defectdojo_utils/defectdojo.py
defectdojo_utils/main.py
defectdojo_utils/nessus.py
defectdojo_utils_kahiroka-0.0.2.dist-info/METADATA
defectdojo_utils_kahiroka-0.0.2.dist-info/WHEEL
defectdojo_utils_kahiroka-0.0.2.dist-info/entry_points.txt
defectdojo_utils_kahiroka-0.0.2.dist-info/top_level.txt
defectdojo_utils_kahiroka-0.0.2.dist-info/RECORD
